LICENSE
MANIFEST.in
README.md
setup.py
wordle_game/__init__.py
wordle_game/app.py
wordle_game/app_wrapper.py
wordle_game/helper.c
wordle_game/helper.pyx
wordle_game/main.py
wordle_game/solver.py
wordle_game/test_wordle.py
wordle_game/wordle.py
wordle_game.egg-info/PKG-INFO
wordle_game.egg-info/SOURCES.txt
wordle_game.egg-info/dependency_links.txt
wordle_game.egg-info/entry_points.txt
wordle_game.egg-info/top_level.txt
wordle_game/data/wordle-allowed-guesses.txt
wordle_game/data/wordle-answers-alphabetical.txt