Metadata-Version: 2.1
Name: wordle-game
Version: 0.1.2
Summary: Play and solve Wordle games.
Home-page: https://github.com/ahaque12/wordle-game
Author: Adnan Haque
Author-email: ahaque12@gmail.com
License: UNKNOWN
Project-URL: Source, https://github.com/ahaque12/wordle-game
Project-URL: Tracker, https://github.com/ahaque12/wordle-game/issues
Keywords: wordle game solver
Platform: UNKNOWN
Classifier: Programming Language :: Python :: 3
Classifier: License :: OSI Approved :: MIT License
Classifier: Operating System :: OS Independent
Requires-Python: >=3.6
License-File: LICENSE
